neonx
