Metadata-Version: 1.1
Name: neonx
Version: 0.1.1
Summary: Handles conversion of date from NetworkX graph to Neo4j
Home-page: https://github.com/ducky427/neonx
Author: Rohit Aggarwal
Author-email: rohit.neonx@mailnull.com
License: MIT
Keywords: neonx
Platform: UNKNOWN
Classifier: Development Status :: 2 - Pre-Alpha
Classifier: Intended Audience :: Developers
Classifier: License :: OSI Approved :: MIT License
Classifier: Natural Language :: English
Classifier: Programming Language :: Python :: 2
Classifier: Programming Language :: Python :: 2.6
Classifier: Programming Language :: Python :: 2.7
Classifier: Programming Language :: Python :: 3
Classifier: Programming Language :: Python :: 3.3
